deepfloyd_if/__init__.py
deepfloyd_if/utils.py
deepfloyd_if/model/__init__.py
deepfloyd_if/model/gaussian_diffusion.py
deepfloyd_if/model/losses.py
deepfloyd_if/model/nn.py
deepfloyd_if/model/resample.py
deepfloyd_if/model/respace.py
deepfloyd_if/model/unet.py
deepfloyd_if/modules/__init__.py
deepfloyd_if/modules/base.py
deepfloyd_if/modules/stage_I.py
deepfloyd_if/modules/stage_II.py
deepfloyd_if/modules/stage_III.py
deepfloyd_if/modules/stage_III_sd_x4.py
deepfloyd_if/modules/t5.py
deepfloyd_if/modules/utils.py
deepfloyd_if/pipelines/__init__.py
deepfloyd_if/pipelines/dream.py
deepfloyd_if/pipelines/inpainting.py
deepfloyd_if/pipelines/style_transfer.py
deepfloyd_if/pipelines/super_resolution.py
deepfloyd_if/pipelines/utils.py
deepfloyd_if/resources/p_head_v1.npz
deepfloyd_if/resources/w_head_v1.npz
deepfloyd_if/resources/wm.png
deepfloyd_if/resources/zero_t5-v1_1-xxl_vector.npy
deepfloyd_if-1.0.1.dist-info/LICENSE
deepfloyd_if-1.0.1.dist-info/LICENSE-MODEL
deepfloyd_if-1.0.1.dist-info/METADATA
deepfloyd_if-1.0.1.dist-info/WHEEL
deepfloyd_if-1.0.1.dist-info/top_level.txt
deepfloyd_if-1.0.1.dist-info/RECORD
