Metadata-Version: 2.1
Name: deepfloyd-if
Version: 1.0.1
Summary: DeepFloyd-IF (Imagen Free)
Author: DeepFloyd, StabilityAI
Author-email: shonenkov@gmail.com
License-File: LICENSE
License-File: LICENSE-MODEL
Requires-Dist: tqdm
Requires-Dist: numpy
Requires-Dist: torch (<2.0.0)
Requires-Dist: torchvision
Requires-Dist: omegaconf
Requires-Dist: matplotlib
Requires-Dist: Pillow (>=9.2.0)
Requires-Dist: huggingface-hub (>=0.13.2)
Requires-Dist: transformers (~=4.25.1)
Requires-Dist: accelerate (~=0.15.0)
Requires-Dist: diffusers (~=0.16.0)
Requires-Dist: tokenizers (~=0.13.2)
Requires-Dist: sentencepiece (~=0.1.97)
Requires-Dist: ftfy (~=6.1.1)
Requires-Dist: beautifulsoup4 (~=4.11.1)
